lerum/__init__.py
lerum-0.1.1.dist-info/METADATA
lerum-0.1.1.dist-info/WHEEL
lerum-0.1.1.dist-info/entry_points.txt
lerum-0.1.1.dist-info/RECORD
