Metadata-Version: 2.4
Name: lerum
Version: 0.1.1
Summary: in progress
Requires-Python: >=3.10
